inception/__init__.py
inception/constants.py
inception/inceptionobject.py
inception/argparsers/__init__.py
inception/argparsers/argparser.py
inception/argparsers/autoroot.py
inception/argparsers/bootstrap.py
inception/argparsers/busybox.py
inception/argparsers/learn.py
inception/argparsers/ls.py
inception/argparsers/make.py
inception/argparsers/plant.py
inception/argparsers/sync.py
inception/argparsers/exceptions/__init__.py
inception/argparsers/exceptions/argparser.py
inception/argparsers/exceptions/makeupdatepkgfailed.py
inception/argparsers/makers/__init__.py
inception/argparsers/makers/maker.py
inception/argparsers/makers/maker_cache.py
inception/argparsers/makers/maker_config.py
inception/argparsers/makers/maker_dnx.py
inception/argparsers/makers/maker_extras.py
inception/argparsers/makers/maker_image.py
inception/argparsers/makers/maker_image_boot.py
inception/argparsers/makers/maker_image_recovery.py
inception/argparsers/makers/maker_installercmd.py
inception/argparsers/makers/maker_odin.py
inception/argparsers/makers/maker_package.py
inception/argparsers/makers/maker_update.py
inception/argparsers/makers/submakers/__init__.py
inception/argparsers/makers/submakers/submaker.py
inception/argparsers/makers/submakers/submaker_adbkeys.py
inception/argparsers/makers/submakers/submaker_apps.py
inception/argparsers/makers/submakers/submaker_busybox.py
inception/argparsers/makers/submakers/submaker_databases.py
inception/argparsers/makers/submakers/submaker_fs.py
inception/argparsers/makers/submakers/submaker_property.py
inception/argparsers/makers/submakers/submaker_settings.py
inception/argparsers/makers/submakers/submaker_supersu.py
inception/argparsers/makers/submakers/submaker_updatescript.py
inception/argparsers/makers/submakers/submaker_updatescriptinit.py
inception/argparsers/makers/submakers/submaker_updatezip.py
inception/argparsers/makers/submakers/submaker_wifi.py
inception/common/__init__.py
inception/common/configsyncer.py
inception/common/database.py
inception_android-0.9.18.dist-info/LICENSE
inception_android-0.9.18.dist-info/METADATA
inception_android-0.9.18.dist-info/WHEEL
inception_android-0.9.18.dist-info/top_level.txt
inception_android-0.9.18.dist-info/RECORD
